odoo/addons/purchase_requisition_blanket_order_report/README.rst
odoo/addons/purchase_requisition_blanket_order_report/__init__.py
odoo/addons/purchase_requisition_blanket_order_report/__manifest__.py
odoo/addons/purchase_requisition_blanket_order_report/i18n/it.po
odoo/addons/purchase_requisition_blanket_order_report/i18n/purchase_requisition_blanket_order_report.pot
odoo/addons/purchase_requisition_blanket_order_report/readme/CONTRIBUTORS.md
odoo/addons/purchase_requisition_blanket_order_report/readme/DESCRIPTION.md
odoo/addons/purchase_requisition_blanket_order_report/report/report_purchase_requisition.xml
odoo/addons/purchase_requisition_blanket_order_report/static/description/icon.png
odoo/addons/purchase_requisition_blanket_order_report/static/description/index.html
odoo14_addon_purchase_requisition_blanket_order_report-14.0.1.0.1.dev4.dist-info/METADATA
odoo14_addon_purchase_requisition_blanket_order_report-14.0.1.0.1.dev4.dist-info/WHEEL
odoo14_addon_purchase_requisition_blanket_order_report-14.0.1.0.1.dev4.dist-info/top_level.txt
odoo14_addon_purchase_requisition_blanket_order_report-14.0.1.0.1.dev4.dist-info/RECORD
